dhapi/__init__.py
dhapi/_version.py
dhapi/main.py
dhapi/config/__init__.py
dhapi/config/logger.py
dhapi/domain/__init__.py
dhapi/domain/deposit.py
dhapi/domain/lotto645_ticket.py
dhapi/domain/user.py
dhapi/endpoint/__init__.py
dhapi/endpoint/lottery_stdout_printer.py
dhapi/endpoint/version_stdout_printer.py
dhapi/meta/__init__.py
dhapi/meta/version_provider.py
dhapi/port/__init__.py
dhapi/port/credentials_provider.py
dhapi/port/lottery_client.py
dhapi/purchase/__init__.py
dhapi/purchase/lotto645_buy_confirmer.py
dhapi/router/__init__.py
dhapi/router/dependency_factory.py
dhapi/router/router.py
dhapi-5.0.0.dist-info/licenses/LICENSE.txt
dhapi-5.0.0.dist-info/METADATA
dhapi-5.0.0.dist-info/WHEEL
dhapi-5.0.0.dist-info/entry_points.txt
dhapi-5.0.0.dist-info/top_level.txt
dhapi-5.0.0.dist-info/RECORD
