Metadata-Version: 2.4
Name: dhapi
Version: 5.0.0
Summary: 동행복권 비공식 API
Home-page: https://github.com/roeniss/dhlottery-api
Author: Roeniss Moon
Author-email: roeniss2@gmail.com
Project-URL: Bug Reports, https://github.com/roeniss/dhlottery-api/issues
Project-URL: Source, https://github.com/roeniss/dhlottery-api/
Keywords: donghaeng,lottery,lotto645,api,korean
Classifier: Development Status :: 5 - Production/Stable
Classifier: Environment :: Console
Classifier: License :: OSI Approved :: MIT License
Classifier: Programming Language :: Python
Requires-Python: >=3.9, <4
License-File: LICENSE.txt
Requires-Dist: beautifulsoup4==4.12.2
Requires-Dist: certifi==2023.11.17
Requires-Dist: charset-normalizer==3.3.2
Requires-Dist: exceptiongroup==1.2.0
Requires-Dist: html5lib==1.1
Requires-Dist: idna==3.6
Requires-Dist: iniconfig==2.0.0
Requires-Dist: packaging==24.2
Requires-Dist: pluggy==1.3.0
Requires-Dist: pytest==7.4.4
Requires-Dist: requests==2.28.2
Requires-Dist: six==1.16.0
Requires-Dist: soupsieve==2.5
Requires-Dist: tomli==2.0.1
Requires-Dist: urllib3==1.26.18
Requires-Dist: webencodings==0.5.1
Requires-Dist: tomli-w==1.0.0
Requires-Dist: mailjet-rest==1.3.4
Requires-Dist: pytz==2024.1
Requires-Dist: pycryptodome==3.19.0
Requires-Dist: typer==0.9.0
Requires-Dist: rich==13.7.0
Requires-Dist: pytest-mock==3.12.0
Requires-Dist: click==8.1.8
Requires-Dist: setuptools_scm==8.3.1
Dynamic: author
Dynamic: author-email
Dynamic: classifier
Dynamic: description
Dynamic: description-content-type
Dynamic: home-page
Dynamic: keywords
Dynamic: license-file
Dynamic: project-url
Dynamic: requires-dist
Dynamic: requires-python
Dynamic: summary
